Workbook

Sheet INTRO
A2: Title: Swing Trading Analysis Model — Automated Trade Decision System
A3: Type: Data & Finance Project
A4: Tools Used: Excel, Technical Indicators, Data Visualization, Risk Modeling
A6: Overview:
A7: A decision-support system designed to streamline swing-trading analysis. The model processes market data and applies a structured technical-analysis framework to produce automated Buy/Sell recommendations.
A9: Key Features:
A11: Automated Technical Indicator Engine: Calculates RSI, EMA, swing highs/lows, and momentum shifts.
A13: Trade Signal Algorithm: Scores setups based on risk–reward, volatility, and trend confirmation.
A15: Entry–Exit Insights: Identifies optimal price zones for swing trades.
A17: Decision Summary Panel: Converts analytics into a clear Buy / Sell / Hold output for easy decision-making.
A19: Interactive Dashboards: Charts highlighting trend structure, signal strength, and performance metrics.
A21: Impact:
A22: Improves the speed and accuracy of swing-trade evaluations, giving traders a simplified, data-driven workflow. Built to support beginners and intermediate traders looking for structured decision logic.

Sheet DATA
A1: stock name | B1: XYZ
A2: current price | B2: 2759 | D2: PIE LABEL | E2: AMOUNT | F2: Bullish | G2: =IF(B14="Bullish",1,0) -> 0 | H2: risk amount | I2: =B24 -> 2000
A3: 44MA candle | B3: 2694.72 | D3: CAPITAL | E3: =B22 -> 100000 | F3: Bearish | G3: =IF(B14="Bearish",1,0) -> 0 | H3: safe capital | I3: =B22-B24 -> 98000
A4: ema 20 | B4: 2829.48 | D4: PROFIT | E4: =MAX(0, (B17-B15)*B25) -> 3967.53 | F4: Range | G4: =IF(B14="Range",1,0) -> 0
A5: ema 50 | B5: 2716.3 | D5: LOSS | E5: =MAX(0, (B15 - B16) * B25) -> 1983.765
A6: ema 200 | B6: 2550.98
A7: RSI | B7: 43.78
A8: supertrend | B8: 2938.67
A9: supertrend color | B9: red
A10: support | B10: 2926.9
A11: vwap auto anchored | B11: 2894.91
A12: Resistance | B12: 2479.9
A13: ATR | B13: 53.98
A14: TREND OUTPUT | B14: =IF((IF(B2>B4,1,0)+IF(B4>B5,1,0)+IF(B5>B6,1,0)+IF(B2>B3,1,0)+IF(B2>B11,1,0)+IF(LEFT(LOWER(B9),3)="green",1,0))>=4,"Bullish", IF((IF(B2<B4,1,0)+IF(B4<B5,1,0)+IF(B5<B6,1,0)+IF(B2<B3,1,0)+IF(B2<B11,1,0)+IF(LEFT(LOWER(B9),3)="red",1,0))>=4,"Bearish","Side Range")) -> Side Range
A15: ENTRY PRICE | B15: =IF(B14="Bullish", MAX(B4,B3,B11) - (0.1 * B13), IF(B14="Bearish", B12 + (0.25 * B13), B10 + (0.25 * B13))) -> 2940.395
A16: STOPLOSS | B16: =IF(B14="Bullish", B15 - (1 * B13), IF(B14="Bearish", B15 - (1 * B13), B10 - (0.5 * B13))) -> 2899.91
A17: TARGET 1 | B17: =B15+(1.5*B13) -> 3021.365
A18: TARGET 2 | B18: =B15+(2.5*B13) -> 3075.345
A19: SWING LOW | B19: =B15 - (1 * B13) -> 2886.415
A20: SWING HIGH | B20: =B15 + (3 * B13) -> 3102.335
A21: EXPECTED LOW | B21: =B15 - (2 * B13) -> 2832.435
A22: capital | B22: 100000
A23: risk % | B23: 0.02
A24: RISK AMOUNT | B24: =B22*B23 -> 2000
A25: POSITIONAL SIZE | B25: =IF(B16>0, ROUNDDOWN(B24 / ABS(B15 - B16), 0), "") -> 49
A26: TRADE SCORE | B26: =ROUND( ( IF(B14="Bullish",2,IF(B14="Bearish",1,0)) + IF(LEFT(LOWER(B9),3)="gre",2,0) + IF(B7>=50,1,0) + IF(B2>B11,1,0) + IF(B2> B4,1,0) + IF(ABS(B2 - B10) <= B13,1,0) ) * (10/8),0) -> 0
A27: TRADE SIGNAL | B27: =IF(B26>=7, IF(B14="Bullish", IF(B15<=B2,"BUY","WAIT"), IF(B14="Bearish", IF(B15>B2,"BREAKOUT BUY","WAIT"), IF(AND(B14="Range", B26>=8, B15<=B2),"BUY","AVOID"))), "AVOID") -> AVOID

Sheet REPORT
B2: TRADE ANALYSIS REPORT
B4: STOCK NAME | D4: =DATA!B1 -> XYZ
B5: CURRENT PRICE | D5: =DATA!B2 -> 2759
B6: TREND | D6: =DATA!B14 -> Side Range
B7: ENTRY PRICE | D7: =DATA!B15 -> 2940.395
B8: STOPLOSS | D8: =DATA!B16 -> 2899.91
B9: TARGET 1 | D9: =DATA!B17 -> 3021.365
B10: TARGET 2 | D10: =DATA!B18 -> 3075.345
B11: SWING HIGH | D11: =DATA!B20 -> 3102.335
B12: SWING LOW | D12: =DATA!B19 -> 2886.415
B13: EXPECTED LOW | D13: =DATA!B21 -> 2832.435
B14: CAPITAL | D14: =DATA!B22 -> 100000
B15: RISK % | D15: =DATA!B23 -> 0.02
B16: POSITIONAL SIZE | D16: =DATA!B25 -> 49
B17: TRADE SCORE | D17: =DATA!B26 -> 0
B18: TRADE SIGNAL | D18: =DATA!B27 -> AVOID
B20: NOTES:
B21: • Position size rounded down for risk safety.
B22: • Entry valid only above breakout confirmation.
B23: • Trend based on EMA stack + VWAP + Supertrend.
B25: Stock Name → name of the selected company
B26: Current Price → market price at analysis
B27: Trend → market direction based on EMAs & indicators
B28: Entry Price → price level to buy after breakout
B29: Stoploss → level to exit if trade fails
B30: Targets → profit-taking levels
B31: Swing High/Low → ATR-based projections
B32: Position Size → shares allowed within risk limit
... B34: Trade Signal → final decision to take or avoid the trade
C36: Disclaimer:
B37: This report is for educational use only and not investment advice; trading involves risk, so
B38: please do your own research carefully. I am not a SEBI-registered advisor and not
B39: responsible for any financial losses incurred. All trade setups, analysis, signals and
B40: calculations shown here are hypothetical and strictly for demonstration purpose only; they
B41: must not be interpreted as buy or sell recommendations. Users must evaluate their
B42: own risk tolerance and consult qualified financial professionals beofre making trades
B43: By using this report, you agree that the author is not liable for losses, market
B44: impacts, or decisions based on this material.
